h4rm3l/__about__.py
h4rm3l/__init__.py
h4rm3l/cmd.py
h4rm3l/csv_cmd.py
h4rm3l/decorator_expressions.py
h4rm3l/decorators.py
h4rm3l/elicitators.py
h4rm3l/evaluate_metrics.py
h4rm3l/harm_evaluation.py
h4rm3l/prompter.py
h4rm3l/synthesizer.py
h4rm3l/test_logs.txt
h4rm3l/data_analysis/prog_synthesi_curves.py
h4rm3l/data_analysis/program_clustering.py
h4rm3l/data_analysis/report_generator.py
h4rm3l/decorator_resources/__init__.py
h4rm3l/decorator_resources/jailbreak-prompt.csv
h4rm3l/decorator_resources/persuasion_taxonomy.jsonl
h4rm3l/model_adapters/anthropic_adapter.py
h4rm3l/model_adapters/anyscale_adapter.py
h4rm3l/model_adapters/olmo_adapter.py
h4rm3l/model_adapters/openai_adapter.py
h4rm3l-0.2.4.dist-info/METADATA
h4rm3l-0.2.4.dist-info/WHEEL
h4rm3l-0.2.4.dist-info/licenses/LICENSE.txt
h4rm3l-0.2.4.dist-info/RECORD
