Metadata-Version: 2.3
Name: h4rm3l
Version: 0.2.4
Project-URL: Documentation, https://mdoumbouya.github.io/h4rm3l/
Project-URL: Issues, https://github.com/mdoumbouya/h4rm3l/issues
Project-URL: Source, https://github.com/mdoumbouya/h4rm3l
Author-email: Moussa Doumbouya <moussa@stanford.edu>
License-Expression: MIT
License-File: LICENSE.txt
Classifier: Development Status :: 4 - Beta
Classifier: Programming Language :: Python
Classifier: Programming Language :: Python :: 3.8
Classifier: Programming Language :: Python :: 3.9
Classifier: Programming Language :: Python :: 3.10
Classifier: Programming Language :: Python :: 3.11
Classifier: Programming Language :: Python :: 3.12
Classifier: Programming Language :: Python :: Implementation :: CPython
Classifier: Programming Language :: Python :: Implementation :: PyPy
Requires-Python: >=3.8
Requires-Dist: ai2-olmo
Requires-Dist: anthropic
Requires-Dist: datasets
Requires-Dist: emoji
Requires-Dist: jinja2
Requires-Dist: matplotlib
Requires-Dist: numpy
Requires-Dist: openai
Requires-Dist: pandasql
Requires-Dist: scienceplots
Requires-Dist: seaborn
Requires-Dist: sentence-transformers
